home_assistant_litedb/__init__.py
home_assistant_litedb/main.py
tests/__init__.py
tests/test_home_assistant_litedb.py
home_assistant_litedb-0.1.0.dist-info/LICENSE
home_assistant_litedb-0.1.0.dist-info/METADATA
home_assistant_litedb-0.1.0.dist-info/WHEEL
home_assistant_litedb-0.1.0.dist-info/entry_points.txt
home_assistant_litedb-0.1.0.dist-info/top_level.txt
home_assistant_litedb-0.1.0.dist-info/RECORD
