Metadata-Version: 2.1
Name: home_assistant_litedb
Version: 0.1.0
Summary: Home Assistant Data Collection Service and Database
Home-page: https://github.com/willmo103/home_assistant_litedb
Author: Will Morris
Author-email: willmorris188@gmail.com
Classifier: Programming Language :: Python :: 3
Classifier: License :: OSI Approved :: MIT License
Classifier: Operating System :: OS Independent
Requires-Python: >=3.6
License-File: LICENSE
Requires-Dist: requests
Requires-Dist: PyYAML
